{
  "id": "f1198f07-4c8a-4ef2-b7f0-4916c2ed129d",
  "prevId": "00000000-0000-0000-0000-000000000000",
  "version": "7",
  "dialect": "postgresql",
  "tables": {
    "public.achievements": {
      "name": "achievements",
      "schema": "",
      "columns": {
        "id": {
          "name": "id",
          "type": "uuid",
          "primaryKey": true,
          "notNull": true,
          "default": "gen_random_uuid()"
        },
        "name": {
          "name": "name",
          "type": "varchar(255)",
          "primaryKey": false,
          "notNull": true
        },
        "description": {
          "name": "description",
          "type": "text",
          "primaryKey": false,
          "notNull": true
        },
        "icon": {
          "name": "icon",
          "type": "varchar(255)",
          "primaryKey": false,
          "notNull": false
        },
        "requirement": {
          "name": "requirement",
          "type": "json",
          "primaryKey": false,
          "notNull": true
        },
        "created_at": {
          "name": "created_at",
          "type": "timestamp",
          "primaryKey": false,
          "notNull": true,
          "default": "now()"
        },
        "updated_at": {
          "name": "updated_at",
          "type": "timestamp",
          "primaryKey": false,
          "notNull": true,
          "default": "now()"
        }
      },
      "indexes": {},
      "foreignKeys": {},
      "compositePrimaryKeys": {},
      "uniqueConstraints": {},
      "policies": {},
      "checkConstraints": {},
      "isRLSEnabled": false
    },
    "public.analytics": {
      "name": "analytics",
      "schema": "",
      "columns": {
        "id": {
          "name": "id",
          "type": "uuid",
          "primaryKey": true,
          "notNull": true,
          "default": "gen_random_uuid()"
        },
        "user_id": {
          "name": "user_id",
          "type": "uuid",
          "primaryKey": false,
          "notNull": true
        },
        "date": {
          "name": "date",
          "type": "timestamp",
          "primaryKey": false,
          "notNull": true
        },
        "total_work_sessions": {
          "name": "total_work_sessions",
          "type": "integer",
          "primaryKey": false,
          "notNull": false,
          "default": 0
        },
        "completed_work_sessions": {
          "name": "completed_work_sessions",
          "type": "integer",
          "primaryKey": false,
          "notNull": false,
          "default": 0
        },
        "total_work_minutes": {
          "name": "total_work_minutes",
          "type": "integer",
          "primaryKey": false,
          "notNull": false,
          "default": 0
        },
        "total_break_minutes": {
          "name": "total_break_minutes",
          "type": "integer",
          "primaryKey": false,
          "notNull": false,
          "default": 0
        },
        "focus_score": {
          "name": "focus_score",
          "type": "integer",
          "primaryKey": false,
          "notNull": false
        },
        "most_productive_time_start": {
          "name": "most_productive_time_start",
          "type": "timestamp",
          "primaryKey": false,
          "notNull": false
        },
        "most_productive_time_end": {
          "name": "most_productive_time_end",
          "type": "timestamp",
          "primaryKey": false,
          "notNull": false
        },
        "completed_tasks": {
          "name": "completed_tasks",
          "type": "integer",
          "primaryKey": false,
          "notNull": false,
          "default": 0
        },
        "created_at": {
          "name": "created_at",
          "type": "timestamp",
          "primaryKey": false,
          "notNull": true,
          "default": "now()"
        },
        "updated_at": {
          "name": "updated_at",
          "type": "timestamp",
          "primaryKey": false,
          "notNull": true,
          "default": "now()"
        }
      },
      "indexes": {},
      "foreignKeys": {
        "analytics_user_id_users_id_fk": {
          "name": "analytics_user_id_users_id_fk",
          "tableFrom": "analytics",
          "tableTo": "users",
          "columnsFrom": [
            "user_id"
          ],
          "columnsTo": [
            "id"
          ],
          "onDelete": "cascade",
          "onUpdate": "no action"
        }
      },
      "compositePrimaryKeys": {},
      "uniqueConstraints": {},
      "policies": {},
      "checkConstraints": {},
      "isRLSEnabled": false
    },
    "public.focus_sounds": {
      "name": "focus_sounds",
      "schema": "",
      "columns": {
        "id": {
          "name": "id",
          "type": "uuid",
          "primaryKey": true,
          "notNull": true,
          "default": "gen_random_uuid()"
        },
        "user_id": {
          "name": "user_id",
          "type": "uuid",
          "primaryKey": false,
          "notNull": false
        },
        "name": {
          "name": "name",
          "type": "varchar(255)",
          "primaryKey": false,
          "notNull": true
        },
        "type": {
          "name": "type",
          "type": "sound_type",
          "typeSchema": "public",
          "primaryKey": false,
          "notNull": true
        },
        "url": {
          "name": "url",
          "type": "varchar(255)",
          "primaryKey": false,
          "notNull": true
        },
        "is_default": {
          "name": "is_default",
          "type": "boolean",
          "primaryKey": false,
          "notNull": false,
          "default": false
        },
        "is_public": {
          "name": "is_public",
          "type": "boolean",
          "primaryKey": false,
          "notNull": false,
          "default": false
        },
        "created_at": {
          "name": "created_at",
          "type": "timestamp",
          "primaryKey": false,
          "notNull": true,
          "default": "now()"
        },
        "updated_at": {
          "name": "updated_at",
          "type": "timestamp",
          "primaryKey": false,
          "notNull": true,
          "default": "now()"
        }
      },
      "indexes": {},
      "foreignKeys": {
        "focus_sounds_user_id_users_id_fk": {
          "name": "focus_sounds_user_id_users_id_fk",
          "tableFrom": "focus_sounds",
          "tableTo": "users",
          "columnsFrom": [
            "user_id"
          ],
          "columnsTo": [
            "id"
          ],
          "onDelete": "cascade",
          "onUpdate": "no action"
        }
      },
      "compositePrimaryKeys": {},
      "uniqueConstraints": {},
      "policies": {},
      "checkConstraints": {},
      "isRLSEnabled": false
    },
    "public.integrations": {
      "name": "integrations",
      "schema": "",
      "columns": {
        "id": {
          "name": "id",
          "type": "uuid",
          "primaryKey": true,
          "notNull": true,
          "default": "gen_random_uuid()"
        },
        "user_id": {
          "name": "user_id",
          "type": "uuid",
          "primaryKey": false,
          "notNull": true
        },
        "type": {
          "name": "type",
          "type": "varchar(50)",
          "primaryKey": false,
          "notNull": true
        },
        "name": {
          "name": "name",
          "type": "varchar(255)",
          "primaryKey": false,
          "notNull": true
        },
        "config": {
          "name": "config",
          "type": "json",
          "primaryKey": false,
          "notNull": true
        },
        "is_active": {
          "name": "is_active",
          "type": "boolean",
          "primaryKey": false,
          "notNull": false,
          "default": true
        },
        "last_synced_at": {
          "name": "last_synced_at",
          "type": "timestamp",
          "primaryKey": false,
          "notNull": false
        },
        "created_at": {
          "name": "created_at",
          "type": "timestamp",
          "primaryKey": false,
          "notNull": true,
          "default": "now()"
        },
        "updated_at": {
          "name": "updated_at",
          "type": "timestamp",
          "primaryKey": false,
          "notNull": true,
          "default": "now()"
        }
      },
      "indexes": {},
      "foreignKeys": {
        "integrations_user_id_users_id_fk": {
          "name": "integrations_user_id_users_id_fk",
          "tableFrom": "integrations",
          "tableTo": "users",
          "columnsFrom": [
            "user_id"
          ],
          "columnsTo": [
            "id"
          ],
          "onDelete": "cascade",
          "onUpdate": "no action"
        }
      },
      "compositePrimaryKeys": {},
      "uniqueConstraints": {},
      "policies": {},
      "checkConstraints": {},
      "isRLSEnabled": false
    },
    "public.session_tasks": {
      "name": "session_tasks",
      "schema": "",
      "columns": {
        "id": {
          "name": "id",
          "type": "uuid",
          "primaryKey": true,
          "notNull": true,
          "default": "gen_random_uuid()"
        },
        "session_id": {
          "name": "session_id",
          "type": "uuid",
          "primaryKey": false,
          "notNull": true
        },
        "task_id": {
          "name": "task_id",
          "type": "uuid",
          "primaryKey": false,
          "notNull": true
        },
        "created_at": {
          "name": "created_at",
          "type": "timestamp",
          "primaryKey": false,
          "notNull": true,
          "default": "now()"
        }
      },
      "indexes": {},
      "foreignKeys": {
        "session_tasks_session_id_sessions_id_fk": {
          "name": "session_tasks_session_id_sessions_id_fk",
          "tableFrom": "session_tasks",
          "tableTo": "sessions",
          "columnsFrom": [
            "session_id"
          ],
          "columnsTo": [
            "id"
          ],
          "onDelete": "cascade",
          "onUpdate": "no action"
        },
        "session_tasks_task_id_tasks_id_fk": {
          "name": "session_tasks_task_id_tasks_id_fk",
          "tableFrom": "session_tasks",
          "tableTo": "tasks",
          "columnsFrom": [
            "task_id"
          ],
          "columnsTo": [
            "id"
          ],
          "onDelete": "cascade",
          "onUpdate": "no action"
        }
      },
      "compositePrimaryKeys": {},
      "uniqueConstraints": {},
      "policies": {},
      "checkConstraints": {},
      "isRLSEnabled": false
    },
    "public.session_templates": {
      "name": "session_templates",
      "schema": "",
      "columns": {
        "id": {
          "name": "id",
          "type": "uuid",
          "primaryKey": true,
          "notNull": true,
          "default": "gen_random_uuid()"
        },
        "user_id": {
          "name": "user_id",
          "type": "uuid",
          "primaryKey": false,
          "notNull": true
        },
        "name": {
          "name": "name",
          "type": "varchar(255)",
          "primaryKey": false,
          "notNull": true
        },
        "work_duration": {
          "name": "work_duration",
          "type": "integer",
          "primaryKey": false,
          "notNull": true
        },
        "short_break_duration": {
          "name": "short_break_duration",
          "type": "integer",
          "primaryKey": false,
          "notNull": true
        },
        "long_break_duration": {
          "name": "long_break_duration",
          "type": "integer",
          "primaryKey": false,
          "notNull": true
        },
        "long_break_interval": {
          "name": "long_break_interval",
          "type": "integer",
          "primaryKey": false,
          "notNull": true
        },
        "auto_start_breaks": {
          "name": "auto_start_breaks",
          "type": "boolean",
          "primaryKey": false,
          "notNull": false,
          "default": false
        },
        "auto_start_pomodoros": {
          "name": "auto_start_pomodoros",
          "type": "boolean",
          "primaryKey": false,
          "notNull": false,
          "default": false
        },
        "is_default": {
          "name": "is_default",
          "type": "boolean",
          "primaryKey": false,
          "notNull": false,
          "default": false
        },
        "created_at": {
          "name": "created_at",
          "type": "timestamp",
          "primaryKey": false,
          "notNull": true,
          "default": "now()"
        },
        "updated_at": {
          "name": "updated_at",
          "type": "timestamp",
          "primaryKey": false,
          "notNull": true,
          "default": "now()"
        }
      },
      "indexes": {},
      "foreignKeys": {
        "session_templates_user_id_users_id_fk": {
          "name": "session_templates_user_id_users_id_fk",
          "tableFrom": "session_templates",
          "tableTo": "users",
          "columnsFrom": [
            "user_id"
          ],
          "columnsTo": [
            "id"
          ],
          "onDelete": "cascade",
          "onUpdate": "no action"
        }
      },
      "compositePrimaryKeys": {},
      "uniqueConstraints": {},
      "policies": {},
      "checkConstraints": {},
      "isRLSEnabled": false
    },
    "public.sessions": {
      "name": "sessions",
      "schema": "",
      "columns": {
        "id": {
          "name": "id",
          "type": "uuid",
          "primaryKey": true,
          "notNull": true,
          "default": "gen_random_uuid()"
        },
        "user_id": {
          "name": "user_id",
          "type": "uuid",
          "primaryKey": false,
          "notNull": true
        },
        "template_id": {
          "name": "template_id",
          "type": "uuid",
          "primaryKey": false,
          "notNull": false
        },
        "type": {
          "name": "type",
          "type": "session_type",
          "typeSchema": "public",
          "primaryKey": false,
          "notNull": true
        },
        "duration": {
          "name": "duration",
          "type": "integer",
          "primaryKey": false,
          "notNull": true
        },
        "started_at": {
          "name": "started_at",
          "type": "timestamp",
          "primaryKey": false,
          "notNull": true
        },
        "completed_at": {
          "name": "completed_at",
          "type": "timestamp",
          "primaryKey": false,
          "notNull": false
        },
        "is_completed": {
          "name": "is_completed",
          "type": "boolean",
          "primaryKey": false,
          "notNull": false,
          "default": false
        },
        "was_interrupted": {
          "name": "was_interrupted",
          "type": "boolean",
          "primaryKey": false,
          "notNull": false,
          "default": false
        },
        "interruption_count": {
          "name": "interruption_count",
          "type": "integer",
          "primaryKey": false,
          "notNull": false,
          "default": 0
        },
        "notes": {
          "name": "notes",
          "type": "text",
          "primaryKey": false,
          "notNull": false
        },
        "created_at": {
          "name": "created_at",
          "type": "timestamp",
          "primaryKey": false,
          "notNull": true,
          "default": "now()"
        },
        "updated_at": {
          "name": "updated_at",
          "type": "timestamp",
          "primaryKey": false,
          "notNull": true,
          "default": "now()"
        }
      },
      "indexes": {},
      "foreignKeys": {
        "sessions_user_id_users_id_fk": {
          "name": "sessions_user_id_users_id_fk",
          "tableFrom": "sessions",
          "tableTo": "users",
          "columnsFrom": [
            "user_id"
          ],
          "columnsTo": [
            "id"
          ],
          "onDelete": "cascade",
          "onUpdate": "no action"
        },
        "sessions_template_id_session_templates_id_fk": {
          "name": "sessions_template_id_session_templates_id_fk",
          "tableFrom": "sessions",
          "tableTo": "session_templates",
          "columnsFrom": [
            "template_id"
          ],
          "columnsTo": [
            "id"
          ],
          "onDelete": "no action",
          "onUpdate": "no action"
        }
      },
      "compositePrimaryKeys": {},
      "uniqueConstraints": {},
      "policies": {},
      "checkConstraints": {},
      "isRLSEnabled": false
    },
    "public.tasks": {
      "name": "tasks",
      "schema": "",
      "columns": {
        "id": {
          "name": "id",
          "type": "uuid",
          "primaryKey": true,
          "notNull": true,
          "default": "gen_random_uuid()"
        },
        "user_id": {
          "name": "user_id",
          "type": "uuid",
          "primaryKey": false,
          "notNull": true
        },
        "title": {
          "name": "title",
          "type": "varchar(255)",
          "primaryKey": false,
          "notNull": true
        },
        "description": {
          "name": "description",
          "type": "text",
          "primaryKey": false,
          "notNull": false
        },
        "priority": {
          "name": "priority",
          "type": "task_priority",
          "typeSchema": "public",
          "primaryKey": false,
          "notNull": false,
          "default": "'medium'"
        },
        "status": {
          "name": "status",
          "type": "task_status",
          "typeSchema": "public",
          "primaryKey": false,
          "notNull": false,
          "default": "'pending'"
        },
        "estimated_pomodoros": {
          "name": "estimated_pomodoros",
          "type": "integer",
          "primaryKey": false,
          "notNull": false
        },
        "actual_pomodoros": {
          "name": "actual_pomodoros",
          "type": "integer",
          "primaryKey": false,
          "notNull": false,
          "default": 0
        },
        "due_date": {
          "name": "due_date",
          "type": "timestamp",
          "primaryKey": false,
          "notNull": false
        },
        "category": {
          "name": "category",
          "type": "varchar(255)",
          "primaryKey": false,
          "notNull": false
        },
        "tags": {
          "name": "tags",
          "type": "json",
          "primaryKey": false,
          "notNull": false
        },
        "created_at": {
          "name": "created_at",
          "type": "timestamp",
          "primaryKey": false,
          "notNull": true,
          "default": "now()"
        },
        "updated_at": {
          "name": "updated_at",
          "type": "timestamp",
          "primaryKey": false,
          "notNull": true,
          "default": "now()"
        }
      },
      "indexes": {},
      "foreignKeys": {
        "tasks_user_id_users_id_fk": {
          "name": "tasks_user_id_users_id_fk",
          "tableFrom": "tasks",
          "tableTo": "users",
          "columnsFrom": [
            "user_id"
          ],
          "columnsTo": [
            "id"
          ],
          "onDelete": "cascade",
          "onUpdate": "no action"
        }
      },
      "compositePrimaryKeys": {},
      "uniqueConstraints": {},
      "policies": {},
      "checkConstraints": {},
      "isRLSEnabled": false
    },
    "public.team_members": {
      "name": "team_members",
      "schema": "",
      "columns": {
        "id": {
          "name": "id",
          "type": "uuid",
          "primaryKey": true,
          "notNull": true,
          "default": "gen_random_uuid()"
        },
        "team_id": {
          "name": "team_id",
          "type": "uuid",
          "primaryKey": false,
          "notNull": true
        },
        "user_id": {
          "name": "user_id",
          "type": "uuid",
          "primaryKey": false,
          "notNull": true
        },
        "is_admin": {
          "name": "is_admin",
          "type": "boolean",
          "primaryKey": false,
          "notNull": false,
          "default": false
        },
        "joined_at": {
          "name": "joined_at",
          "type": "timestamp",
          "primaryKey": false,
          "notNull": true,
          "default": "now()"
        }
      },
      "indexes": {},
      "foreignKeys": {
        "team_members_team_id_teams_id_fk": {
          "name": "team_members_team_id_teams_id_fk",
          "tableFrom": "team_members",
          "tableTo": "teams",
          "columnsFrom": [
            "team_id"
          ],
          "columnsTo": [
            "id"
          ],
          "onDelete": "cascade",
          "onUpdate": "no action"
        },
        "team_members_user_id_users_id_fk": {
          "name": "team_members_user_id_users_id_fk",
          "tableFrom": "team_members",
          "tableTo": "users",
          "columnsFrom": [
            "user_id"
          ],
          "columnsTo": [
            "id"
          ],
          "onDelete": "cascade",
          "onUpdate": "no action"
        }
      },
      "compositePrimaryKeys": {},
      "uniqueConstraints": {},
      "policies": {},
      "checkConstraints": {},
      "isRLSEnabled": false
    },
    "public.team_session_participants": {
      "name": "team_session_participants",
      "schema": "",
      "columns": {
        "id": {
          "name": "id",
          "type": "uuid",
          "primaryKey": true,
          "notNull": true,
          "default": "gen_random_uuid()"
        },
        "team_session_id": {
          "name": "team_session_id",
          "type": "uuid",
          "primaryKey": false,
          "notNull": true
        },
        "user_id": {
          "name": "user_id",
          "type": "uuid",
          "primaryKey": false,
          "notNull": true
        },
        "joined_at": {
          "name": "joined_at",
          "type": "timestamp",
          "primaryKey": false,
          "notNull": true,
          "default": "now()"
        },
        "left_at": {
          "name": "left_at",
          "type": "timestamp",
          "primaryKey": false,
          "notNull": false
        }
      },
      "indexes": {},
      "foreignKeys": {
        "team_session_participants_team_session_id_team_sessions_id_fk": {
          "name": "team_session_participants_team_session_id_team_sessions_id_fk",
          "tableFrom": "team_session_participants",
          "tableTo": "team_sessions",
          "columnsFrom": [
            "team_session_id"
          ],
          "columnsTo": [
            "id"
          ],
          "onDelete": "cascade",
          "onUpdate": "no action"
        },
        "team_session_participants_user_id_users_id_fk": {
          "name": "team_session_participants_user_id_users_id_fk",
          "tableFrom": "team_session_participants",
          "tableTo": "users",
          "columnsFrom": [
            "user_id"
          ],
          "columnsTo": [
            "id"
          ],
          "onDelete": "cascade",
          "onUpdate": "no action"
        }
      },
      "compositePrimaryKeys": {},
      "uniqueConstraints": {},
      "policies": {},
      "checkConstraints": {},
      "isRLSEnabled": false
    },
    "public.team_sessions": {
      "name": "team_sessions",
      "schema": "",
      "columns": {
        "id": {
          "name": "id",
          "type": "uuid",
          "primaryKey": true,
          "notNull": true,
          "default": "gen_random_uuid()"
        },
        "team_id": {
          "name": "team_id",
          "type": "uuid",
          "primaryKey": false,
          "notNull": true
        },
        "creator_id": {
          "name": "creator_id",
          "type": "uuid",
          "primaryKey": false,
          "notNull": true
        },
        "name": {
          "name": "name",
          "type": "varchar(255)",
          "primaryKey": false,
          "notNull": true
        },
        "work_duration": {
          "name": "work_duration",
          "type": "integer",
          "primaryKey": false,
          "notNull": true
        },
        "short_break_duration": {
          "name": "short_break_duration",
          "type": "integer",
          "primaryKey": false,
          "notNull": true
        },
        "long_break_duration": {
          "name": "long_break_duration",
          "type": "integer",
          "primaryKey": false,
          "notNull": true
        },
        "long_break_interval": {
          "name": "long_break_interval",
          "type": "integer",
          "primaryKey": false,
          "notNull": true
        },
        "start_time": {
          "name": "start_time",
          "type": "timestamp",
          "primaryKey": false,
          "notNull": false
        },
        "end_time": {
          "name": "end_time",
          "type": "timestamp",
          "primaryKey": false,
          "notNull": false
        },
        "is_active": {
          "name": "is_active",
          "type": "boolean",
          "primaryKey": false,
          "notNull": false,
          "default": true
        },
        "created_at": {
          "name": "created_at",
          "type": "timestamp",
          "primaryKey": false,
          "notNull": true,
          "default": "now()"
        },
        "updated_at": {
          "name": "updated_at",
          "type": "timestamp",
          "primaryKey": false,
          "notNull": true,
          "default": "now()"
        }
      },
      "indexes": {},
      "foreignKeys": {
        "team_sessions_team_id_teams_id_fk": {
          "name": "team_sessions_team_id_teams_id_fk",
          "tableFrom": "team_sessions",
          "tableTo": "teams",
          "columnsFrom": [
            "team_id"
          ],
          "columnsTo": [
            "id"
          ],
          "onDelete": "cascade",
          "onUpdate": "no action"
        },
        "team_sessions_creator_id_users_id_fk": {
          "name": "team_sessions_creator_id_users_id_fk",
          "tableFrom": "team_sessions",
          "tableTo": "users",
          "columnsFrom": [
            "creator_id"
          ],
          "columnsTo": [
            "id"
          ],
          "onDelete": "no action",
          "onUpdate": "no action"
        }
      },
      "compositePrimaryKeys": {},
      "uniqueConstraints": {},
      "policies": {},
      "checkConstraints": {},
      "isRLSEnabled": false
    },
    "public.teams": {
      "name": "teams",
      "schema": "",
      "columns": {
        "id": {
          "name": "id",
          "type": "uuid",
          "primaryKey": true,
          "notNull": true,
          "default": "gen_random_uuid()"
        },
        "name": {
          "name": "name",
          "type": "varchar(255)",
          "primaryKey": false,
          "notNull": true
        },
        "description": {
          "name": "description",
          "type": "text",
          "primaryKey": false,
          "notNull": false
        },
        "avatar": {
          "name": "avatar",
          "type": "varchar(255)",
          "primaryKey": false,
          "notNull": false
        },
        "created_at": {
          "name": "created_at",
          "type": "timestamp",
          "primaryKey": false,
          "notNull": true,
          "default": "now()"
        },
        "updated_at": {
          "name": "updated_at",
          "type": "timestamp",
          "primaryKey": false,
          "notNull": true,
          "default": "now()"
        }
      },
      "indexes": {},
      "foreignKeys": {},
      "compositePrimaryKeys": {},
      "uniqueConstraints": {},
      "policies": {},
      "checkConstraints": {},
      "isRLSEnabled": false
    },
    "public.user_achievements": {
      "name": "user_achievements",
      "schema": "",
      "columns": {
        "id": {
          "name": "id",
          "type": "uuid",
          "primaryKey": true,
          "notNull": true,
          "default": "gen_random_uuid()"
        },
        "user_id": {
          "name": "user_id",
          "type": "uuid",
          "primaryKey": false,
          "notNull": true
        },
        "achievement_id": {
          "name": "achievement_id",
          "type": "uuid",
          "primaryKey": false,
          "notNull": true
        },
        "unlocked_at": {
          "name": "unlocked_at",
          "type": "timestamp",
          "primaryKey": false,
          "notNull": true,
          "default": "now()"
        }
      },
      "indexes": {},
      "foreignKeys": {
        "user_achievements_user_id_users_id_fk": {
          "name": "user_achievements_user_id_users_id_fk",
          "tableFrom": "user_achievements",
          "tableTo": "users",
          "columnsFrom": [
            "user_id"
          ],
          "columnsTo": [
            "id"
          ],
          "onDelete": "cascade",
          "onUpdate": "no action"
        },
        "user_achievements_achievement_id_achievements_id_fk": {
          "name": "user_achievements_achievement_id_achievements_id_fk",
          "tableFrom": "user_achievements",
          "tableTo": "achievements",
          "columnsFrom": [
            "achievement_id"
          ],
          "columnsTo": [
            "id"
          ],
          "onDelete": "cascade",
          "onUpdate": "no action"
        }
      },
      "compositePrimaryKeys": {},
      "uniqueConstraints": {},
      "policies": {},
      "checkConstraints": {},
      "isRLSEnabled": false
    },
    "public.users": {
      "name": "users",
      "schema": "",
      "columns": {
        "id": {
          "name": "id",
          "type": "uuid",
          "primaryKey": true,
          "notNull": true,
          "default": "gen_random_uuid()"
        },
        "email": {
          "name": "email",
          "type": "varchar(255)",
          "primaryKey": false,
          "notNull": true
        },
        "name": {
          "name": "name",
          "type": "varchar(255)",
          "primaryKey": false,
          "notNull": false
        },
        "password": {
          "name": "password",
          "type": "varchar(255)",
          "primaryKey": false,
          "notNull": false
        },
        "avatar": {
          "name": "avatar",
          "type": "varchar(255)",
          "primaryKey": false,
          "notNull": false
        },
        "preferences": {
          "name": "preferences",
          "type": "json",
          "primaryKey": false,
          "notNull": false
        },
        "created_at": {
          "name": "created_at",
          "type": "timestamp",
          "primaryKey": false,
          "notNull": true,
          "default": "now()"
        },
        "updated_at": {
          "name": "updated_at",
          "type": "timestamp",
          "primaryKey": false,
          "notNull": true,
          "default": "now()"
        }
      },
      "indexes": {},
      "foreignKeys": {},
      "compositePrimaryKeys": {},
      "uniqueConstraints": {
        "users_email_unique": {
          "name": "users_email_unique",
          "nullsNotDistinct": false,
          "columns": [
            "email"
          ]
        }
      },
      "policies": {},
      "checkConstraints": {},
      "isRLSEnabled": false
    }
  },
  "enums": {
    "public.session_type": {
      "name": "session_type",
      "schema": "public",
      "values": [
        "work",
        "short_break",
        "long_break"
      ]
    },
    "public.sound_type": {
      "name": "sound_type",
      "schema": "public",
      "values": [
        "white_noise",
        "nature",
        "ambient",
        "music",
        "custom"
      ]
    },
    "public.task_priority": {
      "name": "task_priority",
      "schema": "public",
      "values": [
        "low",
        "medium",
        "high"
      ]
    },
    "public.task_status": {
      "name": "task_status",
      "schema": "public",
      "values": [
        "pending",
        "in_progress",
        "completed",
        "cancelled"
      ]
    }
  },
  "schemas": {},
  "sequences": {},
  "roles": {},
  "policies": {},
  "views": {},
  "_meta": {
    "columns": {},
    "schemas": {},
    "tables": {}
  }
}